conductor_mcp/__init__.py
conductor_mcp/local_development.py
conductor_mcp/server.py
conductor_mcp/network/__init__.py
conductor_mcp/network/http_proxy.py
conductor_mcp/network/token_manager.py
conductor_mcp/test/__init__.py
conductor_mcp/test/network/__init__.py
conductor_mcp/test/network/http_proxy_test.py
conductor_mcp/test/network/token_manager_test.py
conductor_mcp/test/tools/__init__.py
conductor_mcp/test/tools/workflow_test.py
conductor_mcp/tools/__init__.py
conductor_mcp/tools/task.py
conductor_mcp/tools/workflow.py
conductor_mcp/utils/__init__.py
conductor_mcp/utils/constants.py
conductor_mcp-0.1.7.dist-info/METADATA
conductor_mcp-0.1.7.dist-info/WHEEL
conductor_mcp-0.1.7.dist-info/entry_points.txt
conductor_mcp-0.1.7.dist-info/licenses/LICENSE
conductor_mcp-0.1.7.dist-info/RECORD
