Metadata-Version: 2.4
Name: conductor-mcp
Version: 0.1.7
Summary: MCP server for exposing conductor endpoints.
License-File: LICENSE
Requires-Python: >=3.13
Requires-Dist: asyncio>=3.4.3
Requires-Dist: black>=25.1.0
Requires-Dist: build>=1.2.2.post1
Requires-Dist: click>=8.1.8
Requires-Dist: fastmcp>=2.2.5
Requires-Dist: freezegun>=1.5.1
Requires-Dist: httpx>=0.28.1
Requires-Dist: pytest-asyncio>=0.26.0
Requires-Dist: pytest-httpx>=0.35.0
Requires-Dist: pytest>=8.3.5
Requires-Dist: twine>=6.1.0
